nowui/__init__.py
nowui/components.py
nowui/hooks.py
nowui/router.py
nowui/utilities.py
nowui-0.1.0.dist-info/METADATA
nowui-0.1.0.dist-info/WHEEL
nowui-0.1.0.dist-info/RECORD
