Metadata-Version: 2.1
Name: nowui
Version: 0.1.0
Summary: 
Author: Espoir-Loem
Author-email: hopcy.forcy@gmail.com
Requires-Python: >=3.13,<4.0
Classifier: Programming Language :: Python :: 3
Classifier: Programming Language :: Python :: 3.13
Requires-Dist: kivy (>=2.3.1,<3.0.0)
